myappmaker/__init__.py
myappmaker/__main__.py
myappmaker/appinfo.py
myappmaker/canvasscene.py
myappmaker/config.py
myappmaker/mainwindow.py
myappmaker/prefsmgmt.py
myappmaker/svgutils.py
myappmaker/widgets.py
myappmaker/ourstdlibs/mathutils.py
myappmaker/ourstdlibs/pyl.py
myappmaker/strokesmgmt/__init__.py
myappmaker/strokesmgmt/constants.py
myappmaker/strokesmgmt/displaypanel.py
myappmaker/strokesmgmt/getnotfoundsvg.py
myappmaker/strokesmgmt/recordingdialog.py
myappmaker/strokesmgmt/recordingpanel.py
myappmaker/strokesmgmt/utils.py
myappmaker-0.3.0.dist-info/METADATA
myappmaker-0.3.0.dist-info/WHEEL
myappmaker-0.3.0.dist-info/entry_points.txt
myappmaker-0.3.0.dist-info/top_level.txt
myappmaker-0.3.0.dist-info/RECORD
