Metadata-Version: 2.4
Name: myappmaker
Version: 0.3.0
Summary: Visual desktop app builder for non-techical and technical users
Author-email: Kennedy Richard <kennedy@kennedyrichard.com>
License: Unlicense
Project-URL: Homepage, https://myappmaker.indiesmiths.com
Project-URL: Source Code, https://github.com/IndieSmiths/myappmaker
Project-URL: Forum, https://github.com/IndieSmiths/myappmaker/discussions
Project-URL: Bug Tracker, https://github.com/IndieSmiths/myappmaker/issues
Project-URL: Funding, https://indiesmiths.com/donate
Keywords: desktop,app making,app building,gui,pyside,qt
Classifier: Development Status :: 3 - Alpha
Classifier: Programming Language :: Python :: 3
Classifier: Programming Language :: Python :: Implementation :: CPython
Classifier: Operating System :: OS Independent
Classifier: License :: OSI Approved :: The Unlicense (Unlicense)
Classifier: Topic :: Software Development
Classifier: Topic :: Software Development :: User Interfaces
Classifier: Topic :: Desktop Environment
Classifier: Topic :: Multimedia
Classifier: Intended Audience :: Developers
Classifier: Intended Audience :: End Users/Desktop
Classifier: Intended Audience :: Other Audience
Requires-Python: >=3.7
Requires-Dist: pyside6
Requires-Dist: shapely
